milli-1.8.1.dist-info/METADATA
milli-1.8.1.dist-info/WHEEL
milli-1.8.1.dist-info/license_files/LICENSE
milli/__init__.py
milli/milli.cpython-38-x86_64-linux-gnu.so
milli-1.8.1.dist-info/RECORD
