Metadata-Version: 2.3
Name: milli
Version: 1.8.1
Classifier: Development Status :: 5 - Production/Stable
Classifier: Intended Audience :: Developers
Classifier: License :: OSI Approved :: MIT License
Classifier: Programming Language :: Python
Classifier: Programming Language :: Python :: 3.8
Classifier: Programming Language :: Python :: 3.9
Classifier: Programming Language :: Python :: 3.10
Classifier: Programming Language :: Python :: 3.11
Classifier: Programming Language :: Python :: 3.12
Classifier: Programming Language :: Python :: Implementation :: CPython
Classifier: Programming Language :: Rust
Classifier: Typing :: Typed
License-File: LICENSE
Author: Alexandro Sanchez Bach <alexandro@phi.nz>
Author-email: Alexandro Sanchez Bach <alexandro@phi.nz>
Requires-Python: >=3.8
